hello.py
subota-0.1.0.dist-info/METADATA
subota-0.1.0.dist-info/WHEEL
subota-0.1.0.dist-info/top_level.txt
subota-0.1.0.dist-info/RECORD
